brave_releases_checker/__init__.py
brave_releases_checker/config.py
brave_releases_checker/distributions.py
brave_releases_checker/main.py
brave_releases_checker/version.py
brave_releases_checker-0.3.7.dist-info/entry_points.txt
brave_releases_checker-0.3.7.dist-info/licenses/LICENSE
brave_releases_checker-0.3.7.dist-info/WHEEL
brave_releases_checker-0.3.7.dist-info/METADATA
brave_releases_checker-0.3.7.dist-info/RECORD
