Metadata-Version: 2.4
Name: brave-releases-checker
Version: 0.3.7
Summary: Checks for new Brave Browser releases
Author-email: Dimitris Zlatanidis <dslackw@gmail.com>
Requires-Python: >=3.7
Classifier: Programming Language :: Python :: 3
Classifier: License :: OSI Approved :: MIT License
Classifier: Operating System :: OS Independent
Classifier: Development Status :: 5 - Production/Stable
License-File: LICENSE
Requires-Dist: requests
Requires-Dist: packaging
Requires-Dist: distro
Requires-Dist: notify2
Project-URL: Changelog, https://github.com/dslackw/brave-releases-checker/blob/main/CHANGELOG.md
Project-URL: Documentation, https://github.com/dslackw/brave-releases-checker/blob/main/README.md
Project-URL: Homepage, https://github.com/dslackw/brave-releases-checker
Project-URL: Repository, https://github.com/dslackw/brave-releases-checker.git
